pyiec61850/__init__.py
pyiec61850/_pyiec61850.so
pyiec61850/libiec61850.so
pyiec61850/libiec61850.so.1.6.0
pyiec61850/pyiec61850.py
pyiec61850_ng-1.6.0.7.dist-info/METADATA
pyiec61850_ng-1.6.0.7.dist-info/WHEEL
pyiec61850_ng-1.6.0.7.dist-info/top_level.txt
pyiec61850_ng-1.6.0.7.dist-info/RECORD
