Metadata-Version: 2.4
Name: pyiec61850-ng
Version: 1.6.0.7
Summary: Python bindings for libiec61850 - IEC 61850 protocol implementation
Home-page: https://github.com/f0rw4rd/pyiec61850-ng
Author: f0rw4rd
Author-email: pyiec61850@example.com
License: GPLv3
Project-URL: Bug Reports, https://github.com/f0rw4rd/pyiec61850-ng/issues
Project-URL: Source, https://github.com/f0rw4rd/pyiec61850-ng
Project-URL: Documentation, https://github.com/f0rw4rd/pyiec61850-ng#readme
Keywords: iec61850 mms goose iec-61850 power-systems substation-automation smart-grid scada tase2 iccp iec60870-6
Classifier: Development Status :: 4 - Beta
Classifier: Intended Audience :: Developers
Classifier: Topic :: Software Development :: Libraries :: Python Modules
Classifier: Topic :: System :: Networking
Classifier: Topic :: Software Development :: Embedded Systems
Classifier: License :: OSI Approved :: GNU General Public License v3 (GPLv3)
Classifier: Operating System :: POSIX :: Linux
Classifier: Programming Language :: Python :: 3
Classifier: Programming Language :: Python :: 3.8
Classifier: Programming Language :: Python :: 3.9
Classifier: Programming Language :: Python :: 3.10
Classifier: Programming Language :: Python :: 3.11
Classifier: Programming Language :: Python :: 3.12
Classifier: Programming Language :: Python :: 3.13
Classifier: Programming Language :: Python :: Implementation :: CPython
Requires-Python: >=3.8
Dynamic: author
Dynamic: author-email
Dynamic: classifier
Dynamic: description
Dynamic: description-content-type
Dynamic: home-page
Dynamic: keywords
Dynamic: license
Dynamic: project-url
Dynamic: requires-python
Dynamic: summary
